{
    "name": "Reservation",
    "fields": [],
    "relationships": [
        {
            "relationshipType": "one-to-one",
            "otherEntityName": "court",
            "otherEntityRelationshipName": "reservation",
            "relationshipName": "court",
            "otherEntityField": "id",
            "ownerSide": true
        },
        {
            "relationshipType": "one-to-one",
            "otherEntityName": "joueur",
            "otherEntityRelationshipName": "reservation",
            "relationshipName": "joueur",
            "otherEntityField": "id",
            "ownerSide": true
        },
        {
            "relationshipType": "one-to-one",
            "otherEntityName": "horaire",
            "otherEntityRelationshipName": "reservation",
            "relationshipName": "horaire",
            "otherEntityField": "id",
            "ownerSide": true
        }
    ],
    "changelogDate": "20200121214020",
    "entityTableName": "reservation",
    "dto": "no",
    "pagination": "no",
    "service": "no",
    "jpaMetamodelFiltering": false,
    "fluentMethods": true,
    "readOnly": false,
    "clientRootFolder": "",
    "applications": "*"
}